primeiroPypi/__init__.py
primeiroPypi/primeiroPypi.py
MeuPrimeiroPypi-1.0.dist-info/METADATA
MeuPrimeiroPypi-1.0.dist-info/WHEEL
MeuPrimeiroPypi-1.0.dist-info/top_level.txt
MeuPrimeiroPypi-1.0.dist-info/RECORD
