Metadata-Version: 2.1
Name: MeuPrimeiroPypi
Version: 1.0
Summary: Um Hello World para aprender a subir no twine.
Home-page: 
Author: LRZCalmon / Curso FIAP-PosIA
Author-email: ricardocalmon@gmail.com
Classifier: Programming Language :: Python :: 3
Classifier: License :: OSI Approved :: MIT License
Classifier: Operating System :: OS Independent
Requires-Python: >=3.6
